{"group":[["CPU_Abby","CPU_Cameron","CPU_Chika","CPU_David","CPU_Haru","CPU_Ji-Hoon","CPU_Kian","CPU_Miyu","CPU_Pian-Pian"],["CPU_Chris","CPU_Drum","CPU_Electric","CPU_Haruka","CPU_Hi Hat","CPU_Maria","CPU_Tommy","CPU_Xylo","DFT_Mirvi"],["CPU_Alice","CPU_Bryan","CPU_Displayette","CPU_Elisa","CPU_Marry","CPU_Samantha","CPU_Thessy","DFT_Cam","DFT_Kiara"],["CPU_Danique","CPU_Leon","CPU_Mizuho","CPU_Myrte","CPU_Polly","CPU_Rik","CPU_Theo","DFT_Adione","DFT_Lilian"],["CPU_Araceli","CPU_Barb","CPU_Lucia","CPU_Matt","CPU_Maurits","CPU_Na-Rae","CPU_Rie","DFT_Display","DFT_Sam"]],"diff":{"CPU_Abby":1,"CPU_Alice":3,"CPU_Araceli":5,"CPU_Barb":5,"CPU_Bryan":3,"CPU_Cameron":1,"CPU_Chika":1,"CPU_Chris":2,"CPU_Danique":4,"CPU_David":1,"CPU_Displayette":3,"CPU_Drum":2,"CPU_Electric":2,"CPU_Elisa":3,"CPU_Haru":1,"CPU_Haruka":2,"CPU_Hi Hat":2,"CPU_Ji-Hoon":1,"CPU_Kian":1,"CPU_Leon":4,"CPU_Lucia":5,"CPU_Maria":2,"CPU_Marry":3,"CPU_Matt":5,"CPU_Maurits":5,"CPU_Miyu":1,"CPU_Mizuho":4,"CPU_Myrte":4,"CPU_Na-Rae":5,"CPU_Pian-Pian":1,"CPU_Polly":4,"CPU_Rie":5,"CPU_Rik":4,"CPU_Samantha":3,"CPU_Theo":4,"CPU_Thessy":3,"CPU_Tommy":2,"CPU_Xylo":2,"DFT_Adione":4,"DFT_Cam":3,"DFT_Display":5,"DFT_Kiara":3,"DFT_Lilian":4,"DFT_Mirvi":2,"DFT_Sam":5}}